{"lastId":15,"produs":[{"id":1,"nume":"Pretty Lady","tip":"sanda","pret":"220","culoare":"portocaliu","imagine":"images/produse/s1.jpg"},
 {"id":2,"nume":"Miss Red","tip":"pantof","pret":"210","culoare":"rosu","imagine":"images/produse/p1.jpg"},
 {"id":3,"nume":"Rose Pearl","tip":"decupat","pret":"170","culoare":"roz","imagine":"images/produse/d1.jpg"},
 {"id":4,"nume":"Sunshine","tip":"toc","pret":"110","culoare":"multi","imagine":"images/produse/t1.jpg"},
 {"id":5,"nume":"Skyfall","tip":"pantof","pret":"290","culoare":"albastru","imagine":"images/produse/p2.jpg"},
 {"id":6,"nume":"Peewee","tip":"decupat","pret":"310","culoare":"alb","imagine":"images/produse/d2.jpg"},
 {"id":7,"nume":"Black Widow","tip":"toc","pret":"100","culoare":"negru","imagine":"images/produse/t2.jpg"},
 {"id":8,"nume":"The 50s","tip":"sanda","pret":"120","culoare":"alb","imagine":"images/produse/s3.jpg"},
 {"id":9,"nume":"Grandma","tip":"decupat","pret":"110","culoare":"rosu","imagine":"images/produse/d3.jpg"},
 {"id":10,"nume":"Blood Sugar","tip":"toc","pret":"170","culoare":"rosu","imagine":"images/produse/t3.jpg"},
 {"id":11,"nume":"Spring Break","tip":"sanda","pret":"260","culoare":"rosu","imagine":"images/produse/s4.jpg"},
 {"id":12,"nume":"Burning Desire","tip":"decupat","pret":"230","culoare":"rosu","imagine":"images/produse/p4.jpg"},
 {"id":13,"nume":"Star Wars","tip":"decupat","pret":"100","culoare":"alb","imagine":"images/produse/d4.jpg"},
 {"id":14,"nume":"NightSky","tip":"toc","pret":"200","culoare":"albastru","imagine":"images/produse/t4.jpg"},
 {"id":15,"nume":"Tangled","tip":"decupat","pret":"170","culoare":"multi","imagine":"images/produse/d5.jpg"},
 {"id":16,"nume":"Lollypop","tip":"sanda","pret":"190","culoare":"rosu","imagine":"images/produse/s6.jpg"},
 {"id":17,"nume":"Criminal","tip":"decupat","pret":"310","culoare":"negru","imagine":"images/produse/d6.jpg"},
 {"id":18,"nume":"Dracula","tip":"toc","pret":"90","culoare":"rosu","imagine":"images/produse/t6.jpg"}]}
 